syncy/__init__.py
syncy/cli/__init__.py
syncy/cli/base.py
syncy/cli/gui.py
syncy/cli/utils.py
syncy/cli/validate.py
syncy/cli/wizard.py
syncy/config/__init__.py
syncy/config/rules.py
syncy/config/runtime.py
syncy/core/__init__.py
syncy/core/behaviour.py
syncy/core/connectors.py
syncy/core/diff_engine.py
syncy/core/extractor.py
syncy/core/report.py
syncy/gui/__init__.py
syncy/gui/app.py
syncy/gui/service.py
syncy/gui/state.py
syncy/gui/widgets.py
syncy-0.1.5.dist-info/licenses/LICENSE
syncy-0.1.5.dist-info/METADATA
syncy-0.1.5.dist-info/WHEEL
syncy-0.1.5.dist-info/entry_points.txt
syncy-0.1.5.dist-info/top_level.txt
syncy-0.1.5.dist-info/RECORD
