Metadata-Version: 2.4
Name: syncy
Version: 0.1.5
Summary: Database migration validation tool (SQL Server ↔ PostgreSQL)
Author: 
Classifier: Programming Language :: Python :: 3
Classifier: License :: OSI Approved :: MIT License
Classifier: Operating System :: OS Independent
Requires-Python: >=3.10
License-File: LICENSE
Requires-Dist: click>=8.1.0
Requires-Dist: pyodbc>=5.0.0
Requires-Dist: psycopg2-binary>=2.9.9
Requires-Dist: Jinja2>=3.1.2
Requires-Dist: PyYAML>=6.0.1
Requires-Dist: sqlparse>=0.4.4
Requires-Dist: ttkbootstrap>=1.10.1
Dynamic: classifier
Dynamic: license-file
Dynamic: requires-dist
Dynamic: requires-python
Dynamic: summary
